setup.cfg
setup.py
scripts/yoda
yoda/__init__.py
yoda/config.py
yoda/logger.py
yoda/repository.py
yoda/subcommands.py
yoda/version.py
yoda/workspace.py
yoda.egg-info/PKG-INFO
yoda.egg-info/SOURCES.txt
yoda.egg-info/dependency_links.txt
yoda.egg-info/requires.txt
yoda.egg-info/top_level.txt
yoda/adapter/__init__.py
yoda/adapter/abstract.py
yoda/adapter/git.py
yoda/subcommand/__init__.py
yoda/subcommand/config.py
yoda/subcommand/jump.py
yoda/subcommand/show.py
yoda/subcommand/status.py
yoda/subcommand/update.py
yoda/subcommand/workspace.py