Metadata-Version: 1.0
Name: yoda
Version: 0.1.2.1
Summary: Multiple repositories management
Home-page: https://github.com/Numergy/yoda
Author: UNKNOWN
Author-email: UNKNOWN
License: GPLv3
Platform: UNKNOWN
